minetotg/__init__.py
minetotg/__main__.py
minetotg/main.py
minetotg-1.1.1.dist-info/licenses/LICENSE
minetotg-1.1.1.dist-info/METADATA
minetotg-1.1.1.dist-info/WHEEL
minetotg-1.1.1.dist-info/top_level.txt
minetotg-1.1.1.dist-info/RECORD
