Metadata-Version: 2.4
Name: minetotg
Version: 1.1.1
Summary: A tool that reformat string with Minecraft text formatting to Telegram HTML.
Author-email: R0boji <roboji.public@internet.ru>
License-Expression: MIT
Project-URL: Homepage, https://github.com/R0boji/minetotg
Project-URL: Issues, https://github.com/R0boji/minetotg/issues
Project-URL: GitVerse, https://gitverse.ru/roboji/minetotg
Keywords: Telegram,Formatting,Minecraft
Classifier: Programming Language :: Python :: 3
Classifier: Programming Language :: Python :: 3.8
Classifier: Programming Language :: Python :: 3.9
Classifier: Programming Language :: Python :: 3.10
Classifier: Programming Language :: Python :: 3.11
Classifier: Programming Language :: Python :: 3.12
Classifier: Programming Language :: Python :: 3.13
Classifier: Environment :: Console
Classifier: Intended Audience :: Developers
Classifier: Topic :: Text Processing :: Markup
Classifier: Operating System :: OS Independent
Classifier: Development Status :: 5 - Production/Stable
Requires-Python: >=3.8
License-File: LICENSE
Dynamic: license-file
